{
  "Name": "Level0",
  "Bounds": [
    {
      "Centre": {
        "X": 540,
        "Y": 0
      },
      "Size": {
        "X": 1080,
        "Y": 20
      },
      "Rotation": 0
    },
    {
      "Centre": {
        "X": 540,
        "Y": 720
      },
      "Size": {
        "X": 1080,
        "Y": 20
      },
      "Rotation": 0
    },
    {
      "Centre": {
        "X": 0,
        "Y": 360
      },
      "Size": {
        "X": 20,
        "Y": 720
      },
      "Rotation": 0
    },
    {
      "Centre": {
        "X": 1080,
        "Y": 360
      },
      "Size": {
        "X": 20,
        "Y": 720
      },
      "Rotation": 0
    },
    {
      "Centre": {
        "X": 540,
        "Y": 360
      },
      "Size": {
        "X": 100,
        "Y": 100
      },
      "Rotation": 0.3926991
    }
  ],
  "GrapplePoints": [
    {
      "X": 512.9402,
      "Y": 294.67184
    },
    {
      "X": 474.67184,
      "Y": 387.0598
    },
    {
      "X": 567.0598,
      "Y": 425.32816
    },
    {
      "X": 605.3281,
      "Y": 332.9402
    }
  ],
  "SpawnPoint": {
    "Centre": {
      "X": 100,
      "Y": 100
    },
    "Rotation": 0
  }
}